ascend/__init__.py
ascend-0.0.1.dist-info/METADATA
ascend-0.0.1.dist-info/WHEEL
ascend-0.0.1.dist-info/top_level.txt
ascend-0.0.1.dist-info/RECORD
